{
  "type": "FeatureCollection",
  "features": [
    {
      "type": "Feature",
      "id": "wwi_start",
      "properties": {
        "title": "World War I begins",
        "start_date": "1914-07-28",
        "end_date": "1914-07-28"
      },
      "geometry": {
        "type": "Point",
        "coordinates": [13.4050, 52.5200]
      }
    }
  ]
}
